pyhts/_HFModel.py
pyhts/__init__.py
pyhts/_accuracy.py
pyhts/_dataset.py
pyhts/_forecaster.py
pyhts/_hierarchy.py
pyhts/_reconciliation.py
pyhts/data/Tourism.csv
pyhts-0.2.0.dist-info/LICENSE
pyhts-0.2.0.dist-info/METADATA
pyhts-0.2.0.dist-info/WHEEL
pyhts-0.2.0.dist-info/top_level.txt
pyhts-0.2.0.dist-info/RECORD
