Metadata-Version: 2.1
Name: pyhts
Version: 0.2.0
Summary: A package for forecasting reconciliation.
Home-page: https://github.com/AngelPone/pyhts
Author: Bohan Zhang
Author-email: bhnzhang@outlook.com
License: BSD-3-Clause
Classifier: Programming Language :: Python :: 3
License-File: LICENSE
Requires-Dist: numpy
Requires-Dist: pandas
Requires-Dist: statsforecast
